{
  "provider": "dicebear",
  "version": "9.x",
  "backgroundColor": "ffdfbf,ffd5dc,d1d4f9,c0aede,b6e3f4",
  "styles": [
    "adventurer",
    "adventurer-neutral",
    "avataaars",
    "avataaars-neutral",
    "big-ears",
    "big-ears-neutral",
    "big-smile",
    "bottts",
    "bottts-neutral",
    "croodles",
    "croodles-neutral",
    "dylan",
    "fun-emoji",
    "identicon",
    "lorelei",
    "lorelei-neutral",
    "micah",
    "miniavs",
    "notionists",
    "notionists-neutral",
    "open-peeps",
    "personas",
    "pixel-art",
    "pixel-art-neutral",
    "rings",
    "shapes",
    "thumbs",
    "toon-head"
  ],
  "seeds": [
    "red-picantes-01",
    "red-picantes-02",
    "red-picantes-03",
    "red-picantes-04",
    "red-picantes-05",
    "red-picantes-06",
    "red-picantes-07",
    "red-picantes-08",
    "red-picantes-09",
    "red-picantes-10",
    "red-picantes-11",
    "red-picantes-12",
    "red-picantes-13",
    "red-picantes-14",
    "red-picantes-15",
    "red-picantes-16",
    "red-picantes-17",
    "red-picantes-18",
    "red-picantes-19",
    "red-picantes-20",
    "red-picantes-21",
    "red-picantes-22",
    "red-picantes-23",
    "red-picantes-24",
    "red-picantes-25",
    "red-picantes-26",
    "red-picantes-27",
    "red-picantes-28",
    "red-picantes-29",
    "red-picantes-30",
    "red-picantes-31",
    "red-picantes-32",
    "red-picantes-33",
    "red-picantes-34",
    "red-picantes-35",
    "red-picantes-36",
    "red-picantes-37",
    "red-picantes-38",
    "red-picantes-39",
    "red-picantes-40",
    "red-picantes-41",
    "red-picantes-42",
    "red-picantes-43",
    "red-picantes-44",
    "red-picantes-45",
    "red-picantes-46",
    "red-picantes-47",
    "red-picantes-48"
  ]
}
